asure/__init__.py
asure/exceptions/__init__.py
asure/models/__init__.py
asure/models/routes/__init__.py
asure/models/websocket/__init__.py
asure/primitive/__init__.py
asure/primitive/useful.py
asure/request/__init__.py
asure/request/body.py
asure/request/headers.py
asure/request/params.py
asure/request/response.py
asure/request/useful.py
asure/resource/__init__.py
asure/template/__init__.py
asure/template/useful.py
asure-0.1.0.dist-info/WHEEL
asure-0.1.0.dist-info/METADATA
asure-0.1.0.dist-info/RECORD
