Metadata-Version: 2.1
Name: asure
Version: 0.1.0
Summary: 
Author: JorgeFernando
Author-email: jorgebg2016@gmail.com
Requires-Python: >=3.8,<4.0
Classifier: Programming Language :: Python :: 3
Classifier: Programming Language :: Python :: 3.8
Classifier: Programming Language :: Python :: 3.9
Requires-Dist: uvicorn (==0.12.2)
